Workbook

Sheet Cover
A1: TREUN ROC CONTRACTS
A2: TR CONNECT · COMMERCIAL FORECAST & NEW BUSINESS PIPELINE
A4: BOARD PACK
A5: New business leads · Quick BD capture · Monthly impact roll-up · Stage-gate journey
A7: Document control
A8: Classification | B8: CONFIDENTIAL — INTERNAL USE ONLY
A9: Entity | B9: Treun Roc Contracts
A10: System | B10: TR Connect (connect.treunroccontracts.com)
A11: Period | B11: September 2026
A12: Version | B12: 1.0
A13: Prepared | B13: TR Connect / MD Ops
A14: Reviewed
A15: Approved
A16: Generated | B16: 17 Sep 2026 17:25 UK
A19: Purpose
A20: This pack is the board-level commercial forecast for Treun Roc. Staff capture new business via Quick BD Input (Client, Project, Location, Contact, Est. Annual Turnover, Est. Margin, Est. Duration). Monthly Impact is calculated as Est. Annual Turnover ÷ Est. Duration (weeks) — £ per week of programme, labelled Monthly Impact. Leads feed the Connect journey: Quick BD → Tender/Quote → Jobs board (QUOTED → TENDERED → UPCOMING → LIVE → SNAGGING → COMPLETED) → delivery → invoice.
A24: CONFIDENTIAL
A25: Not for external distribution. Contains commercially sensitive pipeline information.

Sheet Executive Summary
A1: EXECUTIVE SUMMARY — COMMERCIAL PIPELINE
A2: As at 17 Sep 2026 · Formula: Monthly Impact £ = Annual Turnover ÷ Duration (weeks)
A4: PIPELINE TURNOVER £ | C4: MONTHLY IMPACT £ | E4: WEIGHTED IMPACT £ | G4: BD LEADS (excl. Lost) | I4: AVG MARGIN %
A5: ='Quick BD Input'!T2 | C5: ='Quick BD Input'!T3 | E5: ='Quick BD Input'!T4 | G5: ='Quick BD Input'!T5 | I5: =IFERROR(AVERAGEIF('Quick BD Input'!N5:N54,"<>Lost",'Quick BD Input'!J5:J54),0)
A8: Board narrative (editable)
A9: 1. Quick BD is the single capture door for new business — all users, same fields.
A10: 2. Monthly Impact = Annual Turnover ÷ Duration (weeks). Use this for capacity/cash timing on the forecast.
A11: 3. Probability weighting applied on Stage Gate defaults (Lead 10% → Won 100%).
A12: 4. Pipeline stages align to Connect Jobs board: QUOTED / TENDERED / UPCOMING / LIVE / SNAGGING / COMPLETED.
A13: 5. SAMPLE rows are marked — delete before board circulation.
A15: Stage mix (from Quick BD Input)
A16: Lead | B16: =COUNTIF('Quick BD Input'!N:N,A16)
A17: Prequal | B17: =COUNTIF('Quick BD Input'!N:N,A17)
A18: Tender | B18: =COUNTIF('Quick BD Input'!N:N,A18)
A19: Preferred | B19: =COUNTIF('Quick BD Input'!N:N,A19)
A20: Won | B20: =COUNTIF('Quick BD Input'!N:N,A20)
A21: Lost | B21: =COUNTIF('Quick BD Input'!N:N,A21)
A22: On Hold | B22: =COUNTIF('Quick BD Input'!N:N,A22)

Sheet Quick BD Input
A1: QUICK BD INPUT — NEW BUSINESS CAPTURE | T1: ROLL-UP
A2: Monthly Impact £ = Est. Annual Turnover ÷ Est. Duration (weeks) · Est. Margin £ = Annual Turnover × Margin % · Weighted £ = Monthly Impact × Probability % · Yellow = type here · Green = calculated | S2: Pipeline turnover £ | T2: =SUMIF(N5:N54,"<>Lost",I5:I54)
S3: Monthly impact £ | T3: =SUMIF(N5:N54,"<>Lost",L5:L54)
A4: BD Ref | B4: Date Logged | C4: Logged By | D4: Client Name | E4: Project Name | F4: Project Location | G4: Location Type | H4: Client Contact | I4: Est. Annual Turnover (£) | J4: Est. Margin (%) | K4: Est. Duration (weeks) | L4: Monthly Impact (£) | M4: Est. Margin (£) | N4: Stage | O4: Probability % | P4: Weighted Monthly £ | Q4: Notes | R4: Link Job ID | S4: Weighted monthly £ | T4: =SUMIF(N5:N54,"<>Lost",P5:P54)
A5: BD-2026-001 | B5: 46275 | C5: R. Wilson | D5: SAMPLE — National Rail framework enquiry | E5: Station canopy renewals — Phase 1 | F5: London & South East | G5: Specific | H5: J. Hartley (Commercial) | I5: 4200000 | J5: 0.12 | K5: 52 | L5: =IF(OR(I5="",K5="",K5=0),"",I5/K5) | M5: =IF(OR(I5="",J5=""),"",I5*J5) | N5: Lead | O5: 0.1 | P5: =IF(OR(L5="",O5=""),"",L5*O5) | Q5: SAMPLE — delete before board pack | S5: Lead count (excl Lost) | T5: =COUNTIFS(D5:D54,"<>",N5:N54,"<>Lost")
A6: BD-2026-002 | B6: 46277 | C6: R. Wilson | D6: SAMPLE — Regional healthcare trust | E6: Acute ward refurbishment package | F6: National coverage | G6: National Coverage | H6: S. Patel (Estates) | I6: 1850000 | J6: 0.14 | K6: 40 | L6: =IF(OR(I6="",K6="",K6=0),"",I6/K6) | M6: =IF(OR(I6="",J6=""),"",I6*J6) | N6: Tender | O6: 0.35 | P6: =IF(OR(L6="",O6=""),"",L6*O6) | Q6: SAMPLE — delete before board pack
A7: BD-2026-003 | B7: 46280 | C7: Office | D7: SAMPLE — Logistics developer | E7: Cold-store shell & core (unit 4) | F7: Midlands | G7: Specific | H7: A. Okonkwo | I7: 960000 | J7: 0.11 | K7: 28 | L7: =IF(OR(I7="",K7="",K7=0),"",I7/K7) | M7: =IF(OR(I7="",J7=""),"",I7*J7) | N7: Prequal | O7: 0.2 | P7: =IF(OR(L7="",O7=""),"",L7*O7) | Q7: SAMPLE — delete before board pack
A8: BD-2026-004 | B8: 46281 | C8: R. Wilson | D8: SAMPLE — Local authority education | E8: SEND school expansion | F8: East of England | G8: Specific | H8: M. Crowther | I8: 2400000 | J8: 0.13 | K8: 60 | L8: =IF(OR(I8="",K8="",K8=0),"",I8/K8) | M8: =IF(OR(I8="",J8=""),"",I8*J8) | N8: Preferred | O8: 0.6 | P8: =IF(OR(L8="",O8=""),"",L8*O8) | Q8: SAMPLE — delete before board pack
A9: =IF(D9="","","BD-2026-"&TEXT(ROW()-4,"000")) | L9: =IF(OR(I9="",K9="",K9=0),"",I9/K9) | M9: =IF(OR(I9="",J9=""),"",I9*J9) | P9: =IF(OR(L9="",O9=""),"",L9*O9)
A10: =IF(D10="","","BD-2026-"&TEXT(ROW()-4,"000")) | L10: =IF(OR(I10="",K10="",K10=0),"",I10/K10) | M10: =IF(OR(I10="",J10=""),"",I10*J10) | P10: =IF(OR(L10="",O10=""),"",L10*O10)
A11: =IF(D11="","","BD-2026-"&TEXT(ROW()-4,"000")) | L11: =IF(OR(I11="",K11="",K11=0),"",I11/K11) | M11: =IF(OR(I11="",J11=""),"",I11*J11) | P11: =IF(OR(L11="",O11=""),"",L11*O11)
A12: =IF(D12="","","BD-2026-"&TEXT(ROW()-4,"000")) | L12: =IF(OR(I12="",K12="",K12=0),"",I12/K12) | M12: =IF(OR(I12="",J12=""),"",I12*J12) | P12: =IF(OR(L12="",O12=""),"",L12*O12)
A13: =IF(D13="","","BD-2026-"&TEXT(ROW()-4,"000")) | L13: =IF(OR(I13="",K13="",K13=0),"",I13/K13) | M13: =IF(OR(I13="",J13=""),"",I13*J13) | P13: =IF(OR(L13="",O13=""),"",L13*O13)
A14: =IF(D14="","","BD-2026-"&TEXT(ROW()-4,"000")) | L14: =IF(OR(I14="",K14="",K14=0),"",I14/K14) | M14: =IF(OR(I14="",J14=""),"",I14*J14) | P14: =IF(OR(L14="",O14=""),"",L14*O14)
A15: =IF(D15="","","BD-2026-"&TEXT(ROW()-4,"000")) | L15: =IF(OR(I15="",K15="",K15=0),"",I15/K15) | M15: =IF(OR(I15="",J15=""),"",I15*J15) | P15: =IF(OR(L15="",O15=""),"",L15*O15)
A16: =IF(D16="","","BD-2026-"&TEXT(ROW()-4,"000")) | L16: =IF(OR(I16="",K16="",K16=0),"",I16/K16) | M16: =IF(OR(I16="",J16=""),"",I16*J16) | P16: =IF(OR(L16="",O16=""),"",L16*O16)
A17: =IF(D17="","","BD-2026-"&TEXT(ROW()-4,"000")) | L17: =IF(OR(I17="",K17="",K17=0),"",I17/K17) | M17: =IF(OR(I17="",J17=""),"",I17*J17) | P17: =IF(OR(L17="",O17=""),"",L17*O17)
A18: =IF(D18="","","BD-2026-"&TEXT(ROW()-4,"000")) | L18: =IF(OR(I18="",K18="",K18=0),"",I18/K18) | M18: =IF(OR(I18="",J18=""),"",I18*J18) | P18: =IF(OR(L18="",O18=""),"",L18*O18)
A19: =IF(D19="","","BD-2026-"&TEXT(ROW()-4,"000")) | L19: =IF(OR(I19="",K19="",K19=0),"",I19/K19) | M19: =IF(OR(I19="",J19=""),"",I19*J19) | P19: =IF(OR(L19="",O19=""),"",L19*O19)
A20: =IF(D20="","","BD-2026-"&TEXT(ROW()-4,"000")) | L20: =IF(OR(I20="",K20="",K20=0),"",I20/K20) | M20: =IF(OR(I20="",J20=""),"",I20*J20) | P20: =IF(OR(L20="",O20=""),"",L20*O20)
... A54: =IF(D54="","","BD-2026-"&TEXT(ROW()-4,"000")) | L54: =IF(OR(I54="",K54="",K54=0),"",I54/K54) | M54: =IF(OR(I54="",J54=""),"",I54*J54) | P54: =IF(OR(L54="",O54=""),"",L54*O54)

Sheet Pipeline Forecast
A1: PIPELINE FORECAST — 18-MONTH MONTHLY IMPACT
A2: Each lead’s Monthly Impact (£/week of programme) is placed across months from Start Month for Duration weeks. Edit Start Month on Quick BD via Notes or set below. Default: current month for SAMPLE rows.
A4: BD Ref | B4: Client | C4: Project | D4: Monthly Impact £ | E4: Duration (wks) | F4: Stage | G4: Sep-26 | H4: Oct-26 | I4: Nov-26 | J4: Dec-26 | K4: Jan-27 | L4: Feb-27 | M4: Mar-27 | N4: Apr-27 | O4: May-27 | P4: Jun-27 | Q4: Jul-27 | R4: Aug-27 | S4: Sep-27 | T4: Oct-27 | U4: Nov-27 | V4: Dec-27 | W4: Jan-28 | X4: Feb-28
A5: BD-2026-001 | B5: SAMPLE — National Rail framework enquiry | C5: Station canopy renewals — Phase 1 | D5: ='Quick BD Input'!L5 | E5: ='Quick BD Input'!K5 | F5: ='Quick BD Input'!N5 | G5: =IF($D5="","",$D5) | H5: =IF($D5="","",$D5) | I5: =IF($D5="","",$D5) | J5: =IF($D5="","",$D5) | K5: =IF($D5="","",$D5) | L5: =IF($D5="","",$D5) | M5: =IF($D5="","",$D5) | N5: =IF($D5="","",$D5) | ... R5: =IF($D5="","",$D5)
A6: BD-2026-002 | B6: SAMPLE — Regional healthcare trust | C6: Acute ward refurbishment package | D6: ='Quick BD Input'!L6 | E6: ='Quick BD Input'!K6 | F6: ='Quick BD Input'!N6 | G6: =IF($D6="","",$D6) | H6: =IF($D6="","",$D6) | I6: =IF($D6="","",$D6) | J6: =IF($D6="","",$D6) | K6: =IF($D6="","",$D6) | L6: =IF($D6="","",$D6) | M6: =IF($D6="","",$D6) | N6: =IF($D6="","",$D6) | ... P6: =IF($D6="","",$D6)
A7: BD-2026-003 | B7: SAMPLE — Logistics developer | C7: Cold-store shell & core (unit 4) | D7: ='Quick BD Input'!L7 | E7: ='Quick BD Input'!K7 | F7: ='Quick BD Input'!N7 | G7: =IF($D7="","",$D7) | H7: =IF($D7="","",$D7) | I7: =IF($D7="","",$D7) | J7: =IF($D7="","",$D7) | K7: =IF($D7="","",$D7) | L7: =IF($D7="","",$D7) | M7: =IF($D7="","",$D7)
A8: BD-2026-004 | B8: SAMPLE — Local authority education | C8: SEND school expansion | D8: ='Quick BD Input'!L8 | E8: ='Quick BD Input'!K8 | F8: ='Quick BD Input'!N8 | G8: =IF($D8="","",$D8) | H8: =IF($D8="","",$D8) | I8: =IF($D8="","",$D8) | J8: =IF($D8="","",$D8) | K8: =IF($D8="","",$D8) | L8: =IF($D8="","",$D8) | M8: =IF($D8="","",$D8) | N8: =IF($D8="","",$D8) | ... T8: =IF($D8="","",$D8)
A9: TOTAL MONTHLY IMPACT | G9: =SUM(G5:G8) | H9: =SUM(H5:H8) | I9: =SUM(I5:I8) | J9: =SUM(J5:J8) | K9: =SUM(K5:K8) | L9: =SUM(L5:L8) | M9: =SUM(M5:M8) | N9: =SUM(N5:N8) | ... X9: =SUM(X5:X8)

Sheet Stage Gate
A1: STAGE GATE — CONNECT PROCESS JOURNEY
A3: Intended flow
A4: Quick BD (#/bd) → Tenders / Quotes → Jobs board statuses QUOTED → TENDERED → UPCOMING → LIVE → SNAGGING → COMPLETED → Hours / Progress / Receipts → Invoices / Statements. Mail sits alongside (pin to job).
A7: Stage | B7: Connect surface | C7: State (honest) | D7: Link-up | E7: Owner action
A8: 1. Capture | B8: Quick BD #/bd + Tenders | C8: WIRING (MD HARD) | D8: Creates job QUOTED + BD meta | E8: Ship form + store fields
A9: 2. Bid | B9: Quotes / Tenders | C9: Quotes thin; Tenders stub in src / stronger on live desk | D9: Two desks — pick one start | E9: Unify entry via Quick BD
A10: 3. Win → programme | B10: Jobs #/jobs 6-col board | C10: LIVE — setJobStatus | D10: addJob defaulted UPCOMING (gap) | E10: BD save → status QUOTED
A11: 4. Deliver | B11: Job detail / site / hours / progress | C11: Present; depth varies | D11: Job file is spine | E11: Keep board truthful daily
A12: 5. Cash | B12: Invoices / statements | C12: Present; Xero gap | D12: Hours→VAT invoice incomplete | E12: Licence-bar P3 later
A13: 6. Mail | B13: #/mail + /mail-feed | C13: LIVE static Graph feed (80) | D13: No auto job pin yet | E13: Manual pin; job-link later
A14: 7. Auth / tenancy | B14: staff-auth + live.json | C14: Interim tunnel; P1 tenantId | D14: Door browser GATE pending | E14: Durable host + users
A15: 8. Board forecast | B15: Export .xlsx | C15: THIS workbook | D15: Export from Jobs/Monitor | E15: Wire download button
A17: Sense-check top gaps (2026-09-17)
A18: 1. No Quick BD form live yet — capture gap for new business.
A19: 2. Tenders vs Quotes split confuses pipeline start.
A20: 3. addJob defaults UPCOMING — BD should land QUOTED first.
A21: 4. Mail → job auto-link missing.
A22: 5. Quote → Job one-click win handoff unclear.

Sheet Assumptions
A1: ASSUMPTIONS & FORMULA GLOSSARY
A3: Formula glossary (authoritative)
A4: Term | B4: Definition | C4: Notes
A5: Monthly Impact £ | B5: Est. Annual Turnover ÷ Est. Duration (weeks) | C5: Ryan lock — £ per week of programme, labelled Monthly Impact
A6: Est. Margin £ | B6: Est. Annual Turnover × Est. Margin % | C6: Gross margin money on the opportunity
A7: Weighted Monthly £ | B7: Monthly Impact £ × Probability % | C7: Risk-adjusted impact for board roll-up
A8: Location Type | B8: Specific OR National Coverage | C8: Dropdown on Quick BD Input
A9: Stage probabilities (default) | B9: Lead 10% · Prequal 20% · Tender 35% · Preferred 60% · Won 100% · Lost 0% · On Hold 15% | C9: Override per row
A10: Working year | B10: 52 weeks | C10: Duration measured in calendar weeks
A11: Currency | B11: GBP £ | C11: No FX in this pack
A14: Commercial assumptions (edit as needed)
A15: Margins are estimated gross margins before overhead recovery unless noted.
A16: Annual turnover is the estimated contract value annualised (or total programme value if ≤12 months — state in Notes).
A17: SAMPLE rows must be deleted before external or board circulation.
A18: This workbook does not replace statutory accounts or Xero.

Sheet Audit Log
A1: DOCUMENT AUDIT LOG
A3: Date | B3: Version | C3: Author | D3: Change | E3: Approved by
A4: 46282.726 | B4: 1.0 | C4: TR Connect / MD | D4: Initial board forecast pack + Quick BD Input + Ryan monthly impact formula lock
